[
  {
    "id": 1,
    "name": "Deshi Shahi Cow",
    "type": "Cow",
    "breed": "Local Deshi",
    "price": 120000,
    "weight": 280,
    "age": 3,
    "location": "Bogura",
    "description": "Healthy deshi cow suitable for Qurbani. Well fed with natural খাবার.",
    "image": "https://i.postimg.cc/8Cw9Yx7M/cow1.jpg",
    "category": "Large Animal"
  },
  {
    "id": 2,
    "name": "Friesian Cross Cow",
    "type": "Cow",
    "breed": "Friesian Cross",
    "price": 220000,
    "weight": 420,
    "age": 4,
    "location": "Rajshahi",
    "description": "Big size cow with excellent স্বাস্থ্য and খাদ্যাভ্যাস.",
    "image": "https://i.postimg.cc/FRcXHfZx/cow2.jpg",
    "category": "Large Animal"
  },
  {
    "id": 3,
    "name": "Red Chittagong Cow",
    "type": "Cow",
    "breed": "Red Chittagong",
    "price": 180000,
    "weight": 320,
    "age": 3.5,
    "location": "Chattogram",
    "description": "দেশি উন্নত জাতের গরু, খুবই জনপ্রিয়.",
    "image": "https://i.postimg.cc/4xQJX9v9/cow3.jpg",
    "category": "Large Animal"
  },
  {
    "id": 4,
    "name": "Sahiwal Cow",
    "type": "Cow",
    "breed": "Sahiwal",
    "price": 260000,
    "weight": 450,
    "age": 5,
    "location": "Pabna",
    "description": "Premium dairy and meat cow with strong build.",
    "image": "https://i.postimg.cc/zXqXK8zT/cow4.jpg",
    "category": "Large Animal"
  },
  {
    "id": 5,
    "name": "Local Brown Cow",
    "type": "Cow",
    "breed": "Deshi Brown",
    "price": 140000,
    "weight": 300,
    "age": 3,
    "location": "Sirajganj",
    "description": "Healthy brown cow, ভালো যত্নে বড় করা হয়েছে.",
    "image": "https://i.postimg.cc/7Zp3yJ5y/cow5.jpg",
    "category": "Large Animal"
  },
  {
    "id": 6,
    "name": "Black Bengal Goat",
    "type": "Goat",
    "breed": "Black Bengal",
    "price": 18000,
    "weight": 25,
    "age": 1.5,
    "location": "Kushtia",
    "description": "Popular goat breed in Bangladesh, very tasty meat.",
    "image": "https://i.postimg.cc/d1QXxWQW/goat1.jpg",
    "category": "Small Animal"
  },
  {
    "id": 7,
    "name": "Jamunapari Goat",
    "type": "Goat",
    "breed": "Jamunapari",
    "price": 35000,
    "weight": 40,
    "age": 2,
    "location": "Pabna",
    "description": "Large goat, ideal for Qurbani and ভালো growth.",
    "image": "https://i.postimg.cc/1zYw3r3k/goat2.jpg",
    "category": "Small Animal"
  },
  {
    "id": 8,
    "name": "Khasi Goat",
    "type": "Goat",
    "breed": "Local Khasi",
    "price": 28000,
    "weight": 32,
    "age": 2,
    "location": "Mymensingh",
    "description": "Healthy khasi goat, well-fed and strong.",
    "image": "https://i.postimg.cc/rm9zGgqY/goat3.jpg",
    "category": "Small Animal"
  },
  {
    "id": 9,
    "name": "Boer Cross Goat",
    "type": "Goat",
    "breed": "Boer Cross",
    "price": 42000,
    "weight": 45,
    "age": 2.5,
    "location": "Dhaka",
    "description": "Imported cross breed, big size and fast growth.",
    "image": "https://i.postimg.cc/Y0KfH2mC/goat4.jpg",
    "category": "Small Animal"
  },
  {
    "id": 10,
    "name": "White Deshi Goat",
    "type": "Goat",
    "breed": "Deshi White",
    "price": 20000,
    "weight": 27,
    "age": 1.8,
    "location": "Tangail",
    "description": "Clean and healthy goat, perfect for Qurbani.",
    "image": "https://i.postimg.cc/fW2fK9wq/goat5.jpg",
    "category": "Small Animal"
  }
]